buildout.cfg
debug.ini
deploy.ini
setup.py
site.zcml
zdaemon.conf
zope.conf
log/README.txt
src/bebop/__init__.py
src/bebop/webdav/README.txt
src/bebop/webdav/__init__.py
src/bebop/webdav/bootstrap.py
src/bebop/webdav/configure.zcml
src/bebop/webdav/ftesting.zcml
src/bebop/webdav/ftests.py
src/bebop/webdav/locking.py
src/bebop/webdav/overrides.zcml
src/bebop/webdav/propfind.py
src/bebop/webdav/put.py
src/bebop/webdav/testing.py
src/largeblue/__init__.py
src/largeblue/startup.py
src/largeblue.pages.egg-info/PKG-INFO
src/largeblue.pages.egg-info/SOURCES.txt
src/largeblue.pages.egg-info/dependency_links.txt
src/largeblue.pages.egg-info/entry_points.txt
src/largeblue.pages.egg-info/namespace_packages.txt
src/largeblue.pages.egg-info/not-zip-safe
src/largeblue.pages.egg-info/paster_plugins.txt
src/largeblue.pages.egg-info/requires.txt
src/largeblue.pages.egg-info/top_level.txt
src/largeblue/pages/README.txt
src/largeblue/pages/__init__.py
src/largeblue/pages/configure.zcml
src/largeblue/pages/dependencies.zcml
src/largeblue/pages/event.py
src/largeblue/pages/ftesting.zcml
src/largeblue/pages/ftests.py
src/largeblue/pages/interfaces.py
src/largeblue/pages/overrides.zcml
src/largeblue/pages/page.py
src/largeblue/pages/schema.py
src/largeblue/pages/subscribers.py
src/largeblue/pages/subscribers.zcml
src/largeblue/pages/testing.py
src/largeblue/pages/browser/__init__.py
src/largeblue/pages/browser/configure.zcml
src/largeblue/pages/browser/static_tiny_mce_patch.js
src/largeblue/pages/browser/view.py
src/largeblue/pages/browser/widget.py
var/README.txt