Metadata-Version: 1.0
Name: largeblue.pages
Version: 0.3.1
Summary: A simple approach to making a zope website's pages content managable
Home-page: http://pesto.largeblue.net/trac/browser/largeblue/devel/largeblue.pages
Author: James Arthur
Author-email: firstname.lastname@largeblue.com
License: Public Domain (note, vendor code contained within has own licenses)
Keywords: zope largeblue pages cms wysiwyg webdav orderable
Platform: UNKNOWN
Classifier: Programming Language :: Python
Classifier: Environment :: Web Environment
Classifier: Topic :: Internet :: WWW/HTTP :: WSGI :: Application
Classifier: Framework :: Zope3
Classifier: Intended Audience :: Developers
Classifier: License :: Public Domain
Classifier: Natural Language :: English
